windows_tools.updates-2.2.0-py3.12-nspkg.pth
windows_tools/updates/__init__.py
windows_tools.updates-2.2.0.dist-info/LICENSE
windows_tools.updates-2.2.0.dist-info/METADATA
windows_tools.updates-2.2.0.dist-info/WHEEL
windows_tools.updates-2.2.0.dist-info/namespace_packages.txt
windows_tools.updates-2.2.0.dist-info/top_level.txt
windows_tools.updates-2.2.0.dist-info/RECORD
